{"absolutePath": "FibonacciBalance.sol", "exportedSymbols": {"FibonacciBalance": [66], "FibonacciLib": [127]}, "id": 128, "nodeType": "SourceUnit", "nodes": [{"id": 1, "literals": ["solidity", "^", "0.4", ".22"], "nodeType": "PragmaDirective", "src": "148:24:0"}, {"baseContracts": [], "contractDependencies": [], "contractKind": "contract", "documentation": null, "fullyImplemented": true, "id": 66, "linearizedBaseContracts": [66], "name": "FibonacciBalance", "nodeType": "ContractDefinition", "nodes": [{"constant": false, "id": 3, "name": "fibonacciLibrary", "nodeType": "VariableDeclaration", "scope": 66, "src": "207:31:0", "stateVariable": true, "storageLocation": "default", "typeDescriptions": {"typeIdentifier": "t_address", "typeString": "address"}, "typeName": {"id": 2, "name": "address", "nodeType": "ElementaryTypeName", "src": "207:7:0", "typeDescriptions": {"typeIdentifier": "t_address", "typeString": "address"}}, "value": null, "visibility": "public"}, {"constant": false, "id": 5, "name": "calculatedFibNumber", "nodeType": "VariableDeclaration", "scope": 66, "src": "292:31:0", "stateVariable": true, "storageLocation": "default", "typeDescriptions": {"typeIdentifier": "t_uint256", "typeString": "uint256"}, "typeName": {"id": 4, "name": "uint", "nodeType": "ElementaryTypeName", "src": "292:4:0", "typeDescriptions": {"typeIdentifier": "t_uint256", "typeString": "uint256"}}, "value": null, "visibility": "public"}, {"constant": false, "id": 8, "name": "start", "nodeType": "VariableDeclaration", "scope": 66, "src": "375:21:0", "stateVariable": true, "storageLocation": "default", "typeDescriptions": {"typeIdentifier": "t_uint256", "typeString": "uint256"}, "typeName": {"id": 6, "name": "uint", "nodeType": "ElementaryTypeName", "src": "375:4:0", "typeDescriptions": {"typeIdentifier": "t_uint256", "typeString": "uint256"}}, "value": {"argumentTypes": null, "hexValue": "33", "id": 7, "isConstant": false, "isLValue": false, "isPure": true, "kind": "number", "lValueRequested": false, "nodeType": "Literal", "src": "395:1:0", "subdenomination": null, "typeDescriptions": {"typeIdentifier": "t_rational_3_by_1", "typeString": "int_const 3"}, "value": "3"}, "visibility": "public"}, {"constant": false, "id": 10, "name": "withdrawalCounter", "nodeType": "VariableDeclaration", "scope": 66, "src": "402:29:0", "stateVariable": true, "storageLocation": "default", "typeDescriptions": {"typeIdentifier": "t_uint256", "typeString": "uint256"}, "typeName": {"id": 9, "name": "uint", "nodeType": "ElementaryTypeName", "src": "402:4:0", "typeDescriptions": {"typeIdentifier": "t_uint256", "typeString": "uint256"}}, "value": null, "visibility": "public"}, {"constant": true, "id": 17, "name": "fibSig", "nodeType": "VariableDeclaration", "scope": 66, "src": "477:62:0", "stateVariable": true, "storageLocation": "default", "typeDescriptions": {"typeIdentifier": "t_bytes4", "typeString": "bytes4"}, "typeName": {"id": 11, "name": "bytes4", "nodeType": "ElementaryTypeName", "src": "477:6:0", "typeDescriptions": {"typeIdentifier": "t_bytes4", "typeString": "bytes4"}}, "value": {"argumentTypes": null, "arguments": [{"argumentTypes": null, "arguments": [{"argumentTypes": null, "hexValue": "7365744669626f6e616363692875696e7432353629", "id": 14, "isConstant": false, "isLValue": false, "isPure": true, "kind": "string", "lValueRequested": false, "nodeType": "Literal", "src": "514:23:0", "subdenomination": null, "typeDescriptions": {"typeIdentifier": "t_stringliteral_fe75faab7f487631650dccb3f82e15d62b457feab524cb13fa48de017c7c3876", "typeString": "literal_string \"setFibonacci(uint256)\""}, "value": "setFibonacci(uint256)"}], "expression": {"argumentTypes": [{"typeIdentifier": "t_stringliteral_fe75faab7f487631650dccb3f82e15d62b457feab524cb13fa48de017c7c3876", "typeString": "literal_string \"setFibonacci(uint256)\""}], "id": 13, "name": "sha3", "nodeType": "Identifier", "overloadedDeclarations": [], "referencedDeclaration": 152, "src": "509:4:0", "typeDescriptions": {"typeIdentifier": "t_function_sha3_pure$__$returns$_t_bytes32_$", "typeString": "function () pure returns (bytes32)"}}, "id": 15, "isConstant": false, "isLValue": false, "isPure": true, "kind": "functionCall", "lValueRequested": false, "names": [], "nodeType": "FunctionCall", "src": "509:29:0", "typeDescriptions": {"typeIdentifier": "t_bytes32", "typeString": "bytes32"}}], "expression": {"argumentTypes": [{"typeIdentifier": "t_bytes32", "typeString": "bytes32"}], "id": 12, "isConstant": false, "isLValue": false, "isPure": true, "lValueRequested": false, "nodeType": "ElementaryTypeNameExpression", "src": "502:6:0", "typeDescriptions": {"typeIdentifier": "t_type$_t_bytes4_$", "typeString": "type(bytes4)"}, "typeName": "bytes4"}, "id": 16, "isConstant": false, "isLValue": false, "isPure": true, "kind": "typeConversion", "lValueRequested": false, "names": [], "nodeType": "FunctionCall", "src": "502:37:0", "typeDescriptions": {"typeIdentifier": "t_bytes4", "typeString": "bytes4"}}, "visibility": "internal"}, {"body": {"id": 26, "nodeType": "Block", "src": "651:53:0", "statements": [{"expression": {"argumentTypes": null, "id": 24, "isConstant": false, "isLValue": false, "isPure": false, "lValueRequested": false, "leftHandSide": {"argumentTypes": null, "id": 22, "name": "fibonacciLibrary", "nodeType": "Identifier", "overloadedDeclarations": [], "referencedDeclaration": 3, "src": "661:16:0", "typeDescriptions": {"typeIdentifier": "t_address", "typeString": "address"}}, "nodeType": "Assignment", "operator": "=", "rightHandSide": {"argumentTypes": null, "id": 23, "name": "_fibonacciLibrary", "nodeType": "Identifier", "overloadedDeclarations": [], "referencedDeclaration": 19, "src": "680:17:0", "typeDescriptions": {"typeIdentifier": "t_address", "typeString": "address"}}, "src": "661:36:0", "typeDescriptions": {"typeIdentifier": "t_address", "typeString": "address"}}, "id": 25, "nodeType": "ExpressionStatement", "src": "661:36:0"}]}, "documentation": null, "id": 27, "implemented": true, "isConstructor": true, "isDeclaredConst": false, "modifiers": [], "name": "", "nodeType": "FunctionDefinition", "parameters": {"id": 20, "nodeType": "ParameterList", "parameters": [{"constant": false, "id": 19, "name": "_fibonacciLibrary", "nodeType": "VariableDeclaration", "scope": 27, "src": "609:25:0", "stateVariable": false, "storageLocation": "default", "typeDescriptions": {"typeIdentifier": "t_address", "typeString": "address"}, "typeName": {"id": 18, "name": "address", "nodeType": "ElementaryTypeName", "src": "609:7:0", "typeDescriptions": {"typeIdentifier": "t_address", "typeString": "address"}}, "value": null, "visibility": "internal"}], "src": "608:27:0"}, "payable": true, "returnParameters": {"id": 21, "nodeType": "ParameterList", "parameters": [], "src": "651:0:0"}, "scope": 66, "src": "597:107:0", "stateMutability": "payable", "superFunction": null, "visibility": "public"}, {"body": {"id": 52, "nodeType": "Block", "src": "730:330:0", "statements": [{"expression": {"argumentTypes": null, "id": 32, "isConstant": false, "isLValue": false, "isPure": false, "lValueRequested": false, "leftHandSide": {"argumentTypes": null, "id": 30, "name": "withdrawalCounter", "nodeType": "Identifier", "overloadedDeclarations": [], "referencedDeclaration": 10, "src": "740:17:0", "typeDescriptions": {"typeIdentifier": "t_uint256", "typeString": "uint256"}}, "nodeType": "Assignment", "operator": "+=", "rightHandSide": {"argumentTypes": null, "hexValue": "31", "id": 31, "isConstant": false, "isLValue": false, "isPure": true, "kind": "number", "lValueRequested": false, "nodeType": "Literal", "src": "761:1:0", "subdenomination": null, "typeDescriptions": {"typeIdentifier": "t_rational_1_by_1", "typeString": "int_const 1"}, "value": "1"}, "src": "740:22:0", "typeDescriptions": {"typeIdentifier": "t_uint256", "typeString": "uint256"}}, "id": 33, "nodeType": "ExpressionStatement", "src": "740:22:0"}, {"expression": {"argumentTypes": null, "arguments": [{"argumentTypes": null, "arguments": [{"argumentTypes": null, "id": 37, "name": "fibSig", "nodeType": "Identifier", "overloadedDeclarations": [], "referencedDeclaration": 17, "src": "966:6:0", "typeDescriptions": {"typeIdentifier": "t_bytes4", "typeString": "bytes4"}}, {"argumentTypes": null, "id": 38, "name": "withdrawalCounter", "nodeType": "Identifier", "overloadedDeclarations": [], "referencedDeclaration": 10, "src": "974:17:0", "typeDescriptions": {"typeIdentifier": "t_uint256", "typeString": "uint256"}}], "expression": {"argumentTypes": [{"typeIdentifier": "t_bytes4", "typeString": "bytes4"}, {"typeIdentifier": "t_uint256", "typeString": "uint256"}], "expression": {"argumentTypes": null, "id": 35, "name": "fibonacciLibrary", "nodeType": "Identifier", "overloadedDeclarations": [], "referencedDeclaration": 3, "src": "936:16:0", "typeDescriptions": {"typeIdentifier": "t_address", "typeString": "address"}}, "id": 36, "isConstant": false, "isLValue": false, "isPure": false, "lValueRequested": false, "memberName": "delegatecall", "nodeType": "MemberAccess", "referencedDeclaration": null, "src": "936:29:0", "typeDescriptions": {"typeIdentifier": "t_function_baredelegatecall_nonpayable$__$returns$_t_bool_$", "typeString": "function () returns (bool)"}}, "id": 39, "isConstant": false, "isLValue": false, "isPure": false, "kind": "functionCall", "lValueRequested": false, "names": [], "nodeType": "FunctionCall", "src": "936:56:0", "typeDescriptions": {"typeIdentifier": "t_bool", "typeString": "bool"}}], "expression": {"argumentTypes": [{"typeIdentifier": "t_bool", "typeString": "bool"}], "id": 34, "name": "require", "nodeType": "Identifier", "overloadedDeclarations": [145, 146], "referencedDeclaration": 145, "src": "928:7:0", "typeDescriptions": {"typeIdentifier": "t_function_require_pure$_t_bool_$returns$__$", "typeString": "function (bool) pure"}}, "id": 40, "isConstant": false, "isLValue": false, "isPure": false, "kind": "functionCall", "lValueRequested": false, "names": [], "nodeType": "FunctionCall", "src": "928:65:0", "typeDescriptions": {"typeIdentifier": "t_tuple$__$", "typeString": "tuple()"}}, "id": 41, "nodeType": "ExpressionStatement", "src": "928:65:0"}, {"expression": {"argumentTypes": null, "arguments": [{"argumentTypes": null, "commonType": {"typeIdentifier": "t_uint256", "typeString": "uint256"}, "id": 49, "isConstant": false, "isLValue": false, "isPure": false, "lValueRequested": false, "leftExpression": {"argumentTypes": null, "id": 47, "name": "calculatedFibNumber", "nodeType": "Identifier", "overloadedDeclarations": [], "referencedDeclaration": 5, "src": "1023:19:0", "typeDescriptions": {"typeIdentifier": "t_uint256", "typeString": "uint256"}}, "nodeType": "BinaryOperation", "operator": "*", "rightExpression": {"argumentTypes": null, "hexValue": "31", "id": 48, "isConstant": false, "isLValue": false, "isPure": true, "kind": "number", "lValueRequested": false, "nodeType": "Literal", "src": "1045:7:0", "subdenomination": "ether", "typeDescriptions": {"typeIdentifier": "t_rational_1000000000000000000_by_1", "typeString": "int_const 1000000000000000000"}, "value": "1"}, "src": "1023:29:0", "typeDescriptions": {"typeIdentifier": "t_uint256", "typeString": "uint256"}}], "expression": {"argumentTypes": [{"typeIdentifier": "t_uint256", "typeString": "uint256"}], "expression": {"argumentTypes": null, "expression": {"argumentTypes": null, "id": 42, "name": "msg", "nodeType": "Identifier", "overloadedDeclarations": [], "referencedDeclaration": 142, "src": "1003:3:0", "typeDescriptions": {"typeIdentifier": "t_magic_message", "typeString": "msg"}}, "id": 45, "isConstant": false, "isLValue": false, "isPure": false, "lValueRequested": false, "memberName": "sender", "nodeType": "MemberAccess", "referencedDeclaration": null, "src": "1003:10:0", "typeDescriptions": {"typeIdentifier": "t_address", "typeString": "address"}}, "id": 46, "isConstant": false, "isLValue": false, "isPure": false, "lValueRequested": false, "memberName": "transfer", "nodeType": "MemberAccess", "referencedDeclaration": null, "src": "1003:19:0", "typeDescriptions": {"typeIdentifier": "t_function_transfer_nonpayable$_t_uint256_$returns$__$", "typeString": "function (uint256)"}}, "id": 50, "isConstant": false, "isLValue": false, "isPure": false, "kind": "functionCall", "lValueRequested": false, "names": [], "nodeType": "FunctionCall", "src": "1003:50:0", "typeDescriptions": {"typeIdentifier": "t_tuple$__$", "typeString": "tuple()"}}, "id": 51, "nodeType": "ExpressionStatement", "src": "1003:50:0"}]}, "documentation": null, "id": 53, "implemented": true, "isConstructor": false, "isDeclaredConst": false, "modifiers": [], "name": "withdraw", "nodeType": "FunctionDefinition", "parameters": {"id": 28, "nodeType": "ParameterList", "parameters": [], "src": "727:2:0"}, "payable": false, "returnParameters": {"id": 29, "nodeType": "ParameterList", "parameters": [], "src": "730:0:0"}, "scope": 66, "src": "710:350:0", "stateMutability": "nonpayable", "superFunction": null, "visibility": "public"}, {"body": {"id": 64, "nodeType": "Block", "src": "1139:106:0", "statements": [{"expression": {"argumentTypes": null, "arguments": [{"argumentTypes": null, "arguments": [{"argumentTypes": null, "expression": {"argumentTypes": null, "id": 59, "name": "msg", "nodeType": "Identifier", "overloadedDeclarations": [], "referencedDeclaration": 142, "src": "1228:3:0", "typeDescriptions": {"typeIdentifier": "t_magic_message", "typeString": "msg"}}, "id": 60, "isConstant": false, "isLValue": false, "isPure": false, "lValueRequested": false, "memberName": "data", "nodeType": "MemberAccess", "referencedDeclaration": null, "src": "1228:8:0", "typeDescriptions": {"typeIdentifier": "t_bytes_calldata_ptr", "typeString": "bytes calldata"}}], "expression": {"argumentTypes": [{"typeIdentifier": "t_bytes_calldata_ptr", "typeString": "bytes calldata"}], "expression": {"argumentTypes": null, "id": 57, "name": "fibonacciLibrary", "nodeType": "Identifier", "overloadedDeclarations": [], "referencedDeclaration": 3, "src": "1198:16:0", "typeDescriptions": {"typeIdentifier": "t_address", "typeString": "address"}}, "id": 58, "isConstant": false, "isLValue": false, "isPure": false, "lValueRequested": false, "memberName": "delegatecall", "nodeType": "MemberAccess", "referencedDeclaration": null, "src": "1198:29:0", "typeDescriptions": {"typeIdentifier": "t_function_baredelegatecall_nonpayable$__$returns$_t_bool_$", "typeString": "function () returns (bool)"}}, "id": 61, "isConstant": false, "isLValue": false, "isPure": false, "kind": "functionCall", "lValueRequested": false, "names": [], "nodeType": "FunctionCall", "src": "1198:39:0", "typeDescriptions": {"typeIdentifier": "t_bool", "typeString": "bool"}}], "expression": {"argumentTypes": [{"typeIdentifier": "t_bool", "typeString": "bool"}], "id": 56, "name": "require", "nodeType": "Identifier", "overloadedDeclarations": [145, 146], "referencedDeclaration": 145, "src": "1190:7:0", "typeDescriptions": {"typeIdentifier": "t_function_require_pure$_t_bool_$returns$__$", "typeString": "function (bool) pure"}}, "id": 62, "isConstant": false, "isLValue": false, "isPure": false, "kind": "functionCall", "lValueRequested": false, "names": [], "nodeType": "FunctionCall", "src": "1190:48:0", "typeDescriptions": {"typeIdentifier": "t_tuple$__$", "typeString": "tuple()"}}, "id": 63, "nodeType": "ExpressionStatement", "src": "1190:48:0"}]}, "documentation": null, "id": 65, "implemented": true, "isConstructor": false, "isDeclaredConst": false, "modifiers": [], "name": "", "nodeType": "FunctionDefinition", "parameters": {"id": 54, "nodeType": "ParameterList", "parameters": [], "src": "1129:2:0"}, "payable": false, "returnParameters": {"id": 55, "nodeType": "ParameterList", "parameters": [], "src": "1139:0:0"}, "scope": 66, "src": "1121:124:0", "stateMutability": "nonpayable", "superFunction": null, "visibility": "public"}], "scope": 128, "src": "174:1073:0"}, {"baseContracts": [], "contractDependencies": [], "contractKind": "contract", "documentation": null, "fullyImplemented": true, "id": 127, "linearizedBaseContracts": [127], "name": "FibonacciLib", "nodeType": "ContractDefinition", "nodes": [{"constant": false, "id": 68, "name": "start", "nodeType": "VariableDeclaration", "scope": 127, "src": "1387:17:0", "stateVariable": true, "storageLocation": "default", "typeDescriptions": {"typeIdentifier": "t_uint256", "typeString": "uint256"}, "typeName": {"id": 67, "name": "uint", "nodeType": "ElementaryTypeName", "src": "1387:4:0", "typeDescriptions": {"typeIdentifier": "t_uint256", "typeString": "uint256"}}, "value": null, "visibility": "public"}, {"constant": false, "id": 70, "name": "calculatedFibNumber", "nodeType": "VariableDeclaration", "scope": 127, "src": "1410:31:0", "stateVariable": true, "storageLocation": "default", "typeDescriptions": {"typeIdentifier": "t_uint256", "typeString": "uint256"}, "typeName": {"id": 69, "name": "uint", "nodeType": "ElementaryTypeName", "src": "1410:4:0", "typeDescriptions": {"typeIdentifier": "t_uint256", "typeString": "uint256"}}, "value": null, "visibility": "public"}, {"body": {"id": 79, "nodeType": "Block", "src": "1534:31:0", "statements": [{"expression": {"argumentTypes": null, "id": 77, "isConstant": false, "isLValue": false, "isPure": false, "lValueRequested": false, "leftHandSide": {"argumentTypes": null, "id": 75, "name": "start", "nodeType": "Identifier", "overloadedDeclarations": [], "referencedDeclaration": 68, "src": "1544:5:0", "typeDescriptions": {"typeIdentifier": "t_uint256", "typeString": "uint256"}}, "nodeType": "Assignment", "operator": "=", "rightHandSide": {"argumentTypes": null, "id": 76, "name": "_start", "nodeType": "Identifier", "overloadedDeclarations": [], "referencedDeclaration": 72, "src": "1552:6:0", "typeDescriptions": {"typeIdentifier": "t_uint256", "typeString": "uint256"}}, "src": "1544:14:0", "typeDescriptions": {"typeIdentifier": "t_uint256", "typeString": "uint256"}}, "id": 78, "nodeType": "ExpressionStatement", "src": "1544:14:0"}]}, "documentation": null, "id": 80, "implemented": true, "isConstructor": false, "isDeclaredConst": false, "modifiers": [], "name": "setStart", "nodeType": "FunctionDefinition", "parameters": {"id": 73, "nodeType": "ParameterList", "parameters": [{"constant": false, "id": 72, "name": "_start", "nodeType": "VariableDeclaration", "scope": 80, "src": "1514:11:0", "stateVariable": false, "storageLocation": "default", "typeDescriptions": {"typeIdentifier": "t_uint256", "typeString": "uint256"}, "typeName": {"id": 71, "name": "uint", "nodeType": "ElementaryTypeName", "src": "1514:4:0", "typeDescriptions": {"typeIdentifier": "t_uint256", "typeString": "uint256"}}, "value": null, "visibility": "internal"}], "src": "1513:13:0"}, "payable": false, "returnParameters": {"id": 74, "nodeType": "ParameterList", "parameters": [], "src": "1534:0:0"}, "scope": 127, "src": "1496:69:0", "stateMutability": "nonpayable", "superFunction": null, "visibility": "public"}, {"body": {"id": 91, "nodeType": "Block", "src": "1608:51:0", "statements": [{"expression": {"argumentTypes": null, "id": 89, "isConstant": false, "isLValue": false, "isPure": false, "lValueRequested": false, "leftHandSide": {"argumentTypes": null, "id": 85, "name": "calculatedFibNumber", "nodeType": "Identifier", "overloadedDeclarations": [], "referencedDeclaration": 70, "src": "1618:19:0", "typeDescriptions": {"typeIdentifier": "t_uint256", "typeString": "uint256"}}, "nodeType": "Assignment", "operator": "=", "rightHandSide": {"argumentTypes": null, "arguments": [{"argumentTypes": null, "id": 87, "name": "n", "nodeType": "Identifier", "overloadedDeclarations": [], "referencedDeclaration": 82, "src": "1650:1:0", "typeDescriptions": {"typeIdentifier": "t_uint256", "typeString": "uint256"}}], "expression": {"argumentTypes": [{"typeIdentifier": "t_uint256", "typeString": "uint256"}], "id": 86, "name": "fibonacci", "nodeType": "Identifier", "overloadedDeclarations": [], "referencedDeclaration": 126, "src": "1640:9:0", "typeDescriptions": {"typeIdentifier": "t_function_internal_nonpayable$_t_uint256_$returns$_t_uint256_$", "typeString": "function (uint256) returns (uint256)"}}, "id": 88, "isConstant": false, "isLValue": false, "isPure": false, "kind": "functionCall", "lValueRequested": false, "names": [], "nodeType": "FunctionCall", "src": "1640:12:0", "typeDescriptions": {"typeIdentifier": "t_uint256", "typeString": "uint256"}}, "src": "1618:34:0", "typeDescriptions": {"typeIdentifier": "t_uint256", "typeString": "uint256"}}, "id": 90, "nodeType": "ExpressionStatement", "src": "1618:34:0"}]}, "documentation": null, "id": 92, "implemented": true, "isConstructor": false, "isDeclaredConst": false, "modifiers": [], "name": "setFibonacci", "nodeType": "FunctionDefinition", "parameters": {"id": 83, "nodeType": "ParameterList", "parameters": [{"constant": false, "id": 82, "name": "n", "nodeType": "VariableDeclaration", "scope": 92, "src": "1593:6:0", "stateVariable": false, "storageLocation": "default", "typeDescriptions": {"typeIdentifier": "t_uint256", "typeString": "uint256"}, "typeName": {"id": 81, "name": "uint", "nodeType": "ElementaryTypeName", "src": "1593:4:0", "typeDescriptions": {"typeIdentifier": "t_uint256", "typeString": "uint256"}}, "value": null, "visibility": "internal"}], "src": "1592:8:0"}, "payable": false, "returnParameters": {"id": 84, "nodeType": "ParameterList", "parameters": [], "src": "1608:0:0"}, "scope": 127, "src": "1571:88:0", "stateMutability": "nonpayable", "superFunction": null, "visibility": "public"}, {"body": {"id": 125, "nodeType": "Block", "src": "1716:141:0", "statements": [{"condition": {"argumentTypes": null, "commonType": {"typeIdentifier": "t_uint256", "typeString": "uint256"}, "id": 101, "isConstant": false, "isLValue": false, "isPure": false, "lValueRequested": false, "leftExpression": {"argumentTypes": null, "id": 99, "name": "n", "nodeType": "Identifier", "overloadedDeclarations": [], "referencedDeclaration": 94, "src": "1730:1:0", "typeDescriptions": {"typeIdentifier": "t_uint256", "typeString": "uint256"}}, "nodeType": "BinaryOperation", "operator": "==", "rightExpression": {"argumentTypes": null, "hexValue": "30", "id": 100, "isConstant": false, "isLValue": false, "isPure": true, "kind": "number", "lValueRequested": false, "nodeType": "Literal", "src": "1735:1:0", "subdenomination": null, "typeDescriptions": {"typeIdentifier": "t_rational_0_by_1", "typeString": "int_const 0"}, "value": "0"}, "src": "1730:6:0", "typeDescriptions": {"typeIdentifier": "t_bool", "typeString": "bool"}}, "falseBody": {"condition": {"argumentTypes": null, "commonType": {"typeIdentifier": "t_uint256", "typeString": "uint256"}, "id": 106, "isConstant": false, "isLValue": false, "isPure": false, "lValueRequested": false, "leftExpression": {"argumentTypes": null, "id": 104, "name": "n", "nodeType": "Identifier", "overloadedDeclarations": [], "referencedDeclaration": 94, "src": "1769:1:0", "typeDescriptions": {"typeIdentifier": "t_uint256", "typeString": "uint256"}}, "nodeType": "BinaryOperation", "operator": "==", "rightExpression": {"argumentTypes": null, "hexValue": "31", "id": 105, "isConstant": false, "isLValue": false, "isPure": true, "kind": "number", "lValueRequested": false, "nodeType": "Literal", "src": "1774:1:0", "subdenomination": null, "typeDescriptions": {"typeIdentifier": "t_rational_1_by_1", "typeString": "int_const 1"}, "value": "1"}, "src": "1769:6:0", "typeDescriptions": {"typeIdentifier": "t_bool", "typeString": "bool"}}, "falseBody": {"expression": {"argumentTypes": null, "commonType": {"typeIdentifier": "t_uint256", "typeString": "uint256"}, "id": 121, "isConstant": false, "isLValue": false, "isPure": false, "lValueRequested": false, "leftExpression": {"argumentTypes": null, "arguments": [{"argumentTypes": null, "commonType": {"typeIdentifier": "t_uint256", "typeString": "uint256"}, "id": 114, "isConstant": false, "isLValue": false, "isPure": false, "lValueRequested": false, "leftExpression": {"argumentTypes": null, "id": 112, "name": "n", "nodeType": "Identifier", "overloadedDeclarations": [], "referencedDeclaration": 94, "src": "1825:1:0", "typeDescriptions": {"typeIdentifier": "t_uint256", "typeString": "uint256"}}, "nodeType": "BinaryOperation", "operator": "-", "rightExpression": {"argumentTypes": null, "hexValue": "31", "id": 113, "isConstant": false, "isLValue": false, "isPure": true, "kind": "number", "lValueRequested": false, "nodeType": "Literal", "src": "1829:1:0", "subdenomination": null, "typeDescriptions": {"typeIdentifier": "t_rational_1_by_1", "typeString": "int_const 1"}, "value": "1"}, "src": "1825:5:0", "typeDescriptions": {"typeIdentifier": "t_uint256", "typeString": "uint256"}}], "expression": {"argumentTypes": [{"typeIdentifier": "t_uint256", "typeString": "uint256"}], "id": 111, "name": "fibonacci", "nodeType": "Identifier", "overloadedDeclarations": [], "referencedDeclaration": 126, "src": "1815:9:0", "typeDescriptions": {"typeIdentifier": "t_function_internal_nonpayable$_t_uint256_$returns$_t_uint256_$", "typeString": "function (uint256) returns (uint256)"}}, "id": 115, "isConstant": false, "isLValue": false, "isPure": false, "kind": "functionCall", "lValueRequested": false, "names": [], "nodeType": "FunctionCall", "src": "1815:16:0", "typeDescriptions": {"typeIdentifier": "t_uint256", "typeString": "uint256"}}, "nodeType": "BinaryOperation", "operator": "+", "rightExpression": {"argumentTypes": null, "arguments": [{"argumentTypes": null, "commonType": {"typeIdentifier": "t_uint256", "typeString": "uint256"}, "id": 119, "isConstant": false, "isLValue": false, "isPure": false, "lValueRequested": false, "leftExpression": {"argumentTypes": null, "id": 117, "name": "n", "nodeType": "Identifier", "overloadedDeclarations": [], "referencedDeclaration": 94, "src": "1844:1:0", "typeDescriptions": {"typeIdentifier": "t_uint256", "typeString": "uint256"}}, "nodeType": "BinaryOperation", "operator": "-", "rightExpression": {"argumentTypes": null, "hexValue": "32", "id": 118, "isConstant": false, "isLValue": false, "isPure": true, "kind": "number", "lValueRequested": false, "nodeType": "Literal", "src": "1848:1:0", "subdenomination": null, "typeDescriptions": {"typeIdentifier": "t_rational_2_by_1", "typeString": "int_const 2"}, "value": "2"}, "src": "1844:5:0", "typeDescriptions": {"typeIdentifier": "t_uint256", "typeString": "uint256"}}], "expression": {"argumentTypes": [{"typeIdentifier": "t_uint256", "typeString": "uint256"}], "id": 116, "name": "fibonacci", "nodeType": "Identifier", "overloadedDeclarations": [], "referencedDeclaration": 126, "src": "1834:9:0", "typeDescriptions": {"typeIdentifier": "t_function_internal_nonpayable$_t_uint256_$returns$_t_uint256_$", "typeString": "function (uint256) returns (uint256)"}}, "id": 120, "isConstant": false, "isLValue": false, "isPure": false, "kind": "functionCall", "lValueRequested": false, "names": [], "nodeType": "FunctionCall", "src": "1834:16:0", "typeDescriptions": {"typeIdentifier": "t_uint256", "typeString": "uint256"}}, "src": "1815:35:0", "typeDescriptions": {"typeIdentifier": "t_uint256", "typeString": "uint256"}}, "functionReturnParameters": 98, "id": 122, "nodeType": "Return", "src": "1808:42:0"}, "id": 123, "nodeType": "IfStatement", "src": "1765:85:0", "trueBody": {"expression": {"argumentTypes": null, "commonType": {"typeIdentifier": "t_uint256", "typeString": "uint256"}, "id": 109, "isConstant": false, "isLValue": false, "isPure": false, "lValueRequested": false, "leftExpression": {"argumentTypes": null, "id": 107, "name": "start", "nodeType": "Identifier", "overloadedDeclarations": [], "referencedDeclaration": 68, "src": "1784:5:0", "typeDescriptions": {"typeIdentifier": "t_uint256", "typeString": "uint256"}}, "nodeType": "BinaryOperation", "operator": "+", "rightExpression": {"argumentTypes": null, "hexValue": "31", "id": 108, "isConstant": false, "isLValue": false, "isPure": true, "kind": "number", "lValueRequested": false, "nodeType": "Literal", "src": "1792:1:0", "subdenomination": null, "typeDescriptions": {"typeIdentifier": "t_rational_1_by_1", "typeString": "int_const 1"}, "value": "1"}, "src": "1784:9:0", "typeDescriptions": {"typeIdentifier": "t_uint256", "typeString": "uint256"}}, "functionReturnParameters": 98, "id": 110, "nodeType": "Return", "src": "1777:16:0"}}, "id": 124, "nodeType": "IfStatement", "src": "1726:124:0", "trueBody": {"expression": {"argumentTypes": null, "id": 102, "name": "start", "nodeType": "Identifier", "overloadedDeclarations": [], "referencedDeclaration": 68, "src": "1745:5:0", "typeDescriptions": {"typeIdentifier": "t_uint256", "typeString": "uint256"}}, "functionReturnParameters": 98, "id": 103, "nodeType": "Return", "src": "1738:12:0"}}]}, "documentation": null, "id": 126, "implemented": true, "isConstructor": false, "isDeclaredConst": false, "modifiers": [], "name": "fibonacci", "nodeType": "FunctionDefinition", "parameters": {"id": 95, "nodeType": "ParameterList", "parameters": [{"constant": false, "id": 94, "name": "n", "nodeType": "VariableDeclaration", "scope": 126, "src": "1684:6:0", "stateVariable": false, "storageLocation": "default", "typeDescriptions": {"typeIdentifier": "t_uint256", "typeString": "uint256"}, "typeName": {"id": 93, "name": "uint", "nodeType": "ElementaryTypeName", "src": "1684:4:0", "typeDescriptions": {"typeIdentifier": "t_uint256", "typeString": "uint256"}}, "value": null, "visibility": "internal"}], "src": "1683:8:0"}, "payable": false, "returnParameters": {"id": 98, "nodeType": "ParameterList", "parameters": [{"constant": false, "id": 97, "name": "", "nodeType": "VariableDeclaration", "scope": 126, "src": "1710:4:0", "stateVariable": false, "storageLocation": "default", "typeDescriptions": {"typeIdentifier": "t_uint256", "typeString": "uint256"}, "typeName": {"id": 96, "name": "uint", "nodeType": "ElementaryTypeName", "src": "1710:4:0", "typeDescriptions": {"typeIdentifier": "t_uint256", "typeString": "uint256"}}, "value": null, "visibility": "internal"}], "src": "1709:6:0"}, "scope": 127, "src": "1665:192:0", "stateMutability": "nonpayable", "superFunction": null, "visibility": "internal"}], "scope": 128, "src": "1306:553:0"}], "src": "148:1712:0"}